homebrew/__init__.py
homebrew/cache.py
homebrew/command_line.py
homebrew/homebrew.py
homebrew/printer.py
homebrew-0.2.4.dist-info/LICENSE
homebrew-0.2.4.dist-info/METADATA
homebrew-0.2.4.dist-info/WHEEL
homebrew-0.2.4.dist-info/entry_points.txt
homebrew-0.2.4.dist-info/top_level.txt
homebrew-0.2.4.dist-info/RECORD
