Metadata-Version: 2.1
Name: homebrew
Version: 0.2.4
Summary: Homebrew wrapper
Home-page: https://github.com/igroen/homebrew
Author: Iwan in 't Groen
Author-email: iwanintgroen@gmail.com
License: ISCL
Platform: UNKNOWN
Classifier: License :: OSI Approved :: ISC License (ISCL)
Classifier: Programming Language :: Python :: 3
Classifier: Programming Language :: Python :: 3.7
Classifier: Programming Language :: Python :: 3.8
Classifier: Programming Language :: Python :: 3.9
